{
    "id": 17028,
    "name": "Criminal's dagger",
    "members": false,
    "tradeable": false,
    "tradeable_on_ge": false,
    "stackable": false,
    "noted": false,
    "noteable": false,
    "linked_id": null,
    "equipable": false,
    "cost": 0,
    "lowalch": 0,
    "highalch": 0,
    "weight": 0.453,
    "buy_limit": null,
    "quest_item": [
        "Murder Mystery"
    ],
    "release_date": "09 June 2003",
    "examine": "A flimsy-looking dagger found at the crime scene.",
    "url": "https://oldschool.runescape.wiki/w/Criminal%27s_dagger"
}