{
    "id": 2532,
    "name": "Ghost",
    "incomplete": false,
    "members": false,
    "release_date": "2001-01-04",
    "combat_level": 76,
    "size": 1,
    "hitpoints": 0,
    "max_hit": 0,
    "attack_type": "Melee",
    "attack_speed": 4,
    "aggressive": true,
    "poisonous": false,
    "immune_poison": false,
    "immune_venom": false,
    "weakness": [
        "Salve amulet",
        " Magic"
    ],
    "slayer_monster": true,
    "slayer_level": 1,
    "slayer_xp": 0,
    "slayer_masters": [
        "turael",
        "mazchna"
    ],
    "examine": "Eeek! A ghost!",
    "wiki_name": "Ghost (Lv 29)",
    "wiki_url": "https://oldschool.runescape.wiki/w/Ghost#Lv_29",
    "attack_level": 0,
    "strength_level": 0,
    "defence_level": 0,
    "magic_level": 0,
    "ranged_level": 0,
    "attack_stab": 0,
    "attack_slash": 0,
    "attack_crush": 0,
    "attack_magic": 0,
    "attack_ranged": 0,
    "defence_stab": 0,
    "defence_slash": 0,
    "defence_crush": 0,
    "defence_magic": 0,
    "defence_ranged": 0,
    "attack_accuracy": 0,
    "melee_strength": 0,
    "ranged_strength": 0,
    "magic_damage": 0,
    "drops": [
        {
            "id": 1,
            "name": "Looting bag",
            "quantity": "1",
            "rarity": "1/30",
            "drop_requirements": "<ref>Only dropped by those found in the [[Wilderness]].</ref>{{CiteForum|author=Envision|url=https://archive.fo/5P5mn|title=Drop Rates V2}}"
        },
        {
            "id": 1,
            "name": "Clue scroll (beginner)",
            "quantity": "1",
            "rarity": "Unknown",
            "drop_requirements": null
        }
    ],
    "rare_drop_table": false
}