{
    "id": 3023,
    "name": "Poison spider",
    "last_updated": "2020-12-25",
    "incomplete": true,
    "members": true,
    "release_date": "2002-02-27",
    "combat_level": 64,
    "size": 1,
    "hitpoints": 64,
    "max_hit": 7,
    "attack_type": [
        "stab"
    ],
    "attack_speed": 6,
    "aggressive": true,
    "poisonous": true,
    "venomous": false,
    "immune_poison": false,
    "immune_venom": false,
    "attributes": [],
    "category": [
        "spider"
    ],
    "slayer_monster": true,
    "slayer_level": 1,
    "slayer_xp": 64.0,
    "slayer_masters": [
        "turael",
        "spria",
        "krystilia"
    ],
    "duplicate": false,
    "examine": "I think this spider has been genetically modified.",
    "wiki_name": "Poison spider (Level 64)",
    "wiki_url": "https://oldschool.runescape.wiki/w/Poison_spider#Level_64",
    "attack_level": 50,
    "strength_level": 52,
    "defence_level": 58,
    "magic_level": 1,
    "ranged_level": 1,
    "attack_bonus": 0,
    "strength_bonus": 0,
    "attack_magic": 0,
    "magic_bonus": 0,
    "attack_ranged": 0,
    "ranged_bonus": 0,
    "defence_stab": 20,
    "defence_slash": 17,
    "defence_crush": 10,
    "defence_magic": 14,
    "defence_ranged": 14,
    "drops": [
        {
            "id": 11941,
            "name": "Looting bag",
            "members": true,
            "quantity": "1",
            "noted": false,
            "rarity": 0.3333333333333333,
            "rolls": 1
        },
        {
            "id": 23182,
            "name": "Clue scroll (beginner)",
            "members": false,
            "quantity": "1",
            "noted": false,
            "rarity": 0.0078125,
            "rolls": 1
        },
        {
            "id": 23490,
            "name": "Larran's key",
            "members": true,
            "quantity": "1",
            "noted": false,
            "rarity": 0.005681818181818182,
            "rolls": 1
        },
        {
            "id": 21257,
            "name": "Slayer's enchantment",
            "members": true,
            "quantity": "1",
            "noted": false,
            "rarity": 0.0037174721189591076,
            "rolls": 1
        }
    ]
}