{
    "id": "7242",
    "name": "Black demon",
    "members": true,
    "release_date": "09 June 2016",
    "combat_level": 184,
    "hitpoints": null,
    "max_hit": null,
    "attack_type": null,
    "attack_speed": null,
    "aggressive": true,
    "poisonous": false,
    "immune_poison": false,
    "immune_venon": null,
    "weakness": null,
    "slayer_monster": null,
    "slayer_level": null,
    "slayer_xp": null,
    "slayer_masters": null,
    "examine": null,
    "wiki_url": null,
    "attack_level": 155,
    "strength_level": 158,
    "defence_level": 162,
    "magic_level": 1,
    "ranged_level": 1,
    "attack_stab": 0,
    "attack_slash": 0,
    "attack_crush": 0,
    "attack_magic": 0,
    "attack_ranged": 0,
    "defence_stab": 0,
    "defence_slash": 0,
    "defence_crush": 0,
    "defence_magic": -10,
    "defence_ranged": 0,
    "attack_accuracy": 0,
    "melee_strength": 0,
    "ranged_strength": 0,
    "magic_damage": 0,
    "drops": [
        {
            "id": null,
            "name": "Ashes",
            "quantity": "1",
            "rarity": "Always",
            "drop_requirements": null
        },
        {
            "id": null,
            "name": "Rune med helm",
            "quantity": "1",
            "rarity": "Rare",
            "drop_requirements": null
        },
        {
            "id": null,
            "name": "Rune chainbody",
            "quantity": "1",
            "rarity": "Rare",
            "drop_requirements": null
        },
        {
            "id": null,
            "name": "Looting bag",
            "quantity": "1",
            "rarity": "1/30",
            "drop_requirements": "<ref>Only dropped by those found in the [[Wilderness]].</ref>"
        },
        {
            "id": null,
            "name": "Ensouled demon head",
            "quantity": "1",
            "rarity": "1/35",
            "drop_requirements": null
        },
        {
            "id": null,
            "name": "Larran's key",
            "quantity": "1",
            "rarity": "Rare",
            "drop_requirements": "<ref group=d name=wildytask>Only dropped while on a [[slayer assignment]] given by [[Krystilia]].</ref>"
        },
        {
            "id": null,
            "name": "Mysterious emblem",
            "quantity": "1",
            "rarity": "1/77",
            "drop_requirements": "<ref group=d name=wildytask>Only dropped while on a [[slayer assignment]] given by [[Krystilia]].</ref><ref group=d name=task>Rarities listed for level 172 and 188 respectively</ref>{{CiteTwitter|author=Mod Ash|url=https://twitter.com/JagexAsh/status/872520473749356549|date=7 June 2017|archiveurl=http://archive.fo/swS9N|archivedate=25 Mar 2019|quote=It's calculated off the HP: 1 in (155 - (HP/2)) There's none with HP over 300, but it'd disregard values higher than that.}}"
        },
        {
            "id": null,
            "name": "Slayer's enchantment",
            "quantity": "1",
            "rarity": "1/195",
            "drop_requirements": "<ref group=d name=wildytask /><ref group=d name=task />{{CiteTwitter|author=Mod Ash|url=https://twitter.com/JagexAsh/status/973892117675298816|date=14 March 2018|archiveurl=http://archive.fo/CWYhV|archivedate=5 June 2019|quote=For nastier bosses (e.g. Callisto) it's 1/30. For other things it scales between 1/320 and 1/80 as the NPC's HP scales from 0 to 300.}}"
        },
        {
            "id": null,
            "name": "Clue scroll (hard)",
            "quantity": "1",
            "rarity": "1/128",
            "drop_requirements": "<ref>1/64 if a [[Ring of wealth (i)]] is worn and fought in the [[Wilderness]].</ref>"
        },
        {
            "id": null,
            "name": "Brimstone key",
            "quantity": "1",
            "rarity": "Varies",
            "drop_requirements": "<ref>Only dropped if killed on a [[slayer assignment]] given by [[Konar quo Maten]].</ref>"
        },
        {
            "id": null,
            "name": "Steel battleaxe",
            "quantity": "1",
            "rarity": "Common",
            "drop_requirements": null
        },
        {
            "id": null,
            "name": "Black sword",
            "quantity": "1",
            "rarity": "Common",
            "drop_requirements": null
        },
        {
            "id": null,
            "name": "Black axe",
            "quantity": "1",
            "rarity": "Uncommon",
            "drop_requirements": null
        },
        {
            "id": null,
            "name": "Mithril kiteshield",
            "quantity": "1",
            "rarity": "Uncommon",
            "drop_requirements": null
        },
        {
            "id": null,
            "name": "Air rune",
            "quantity": "50",
            "rarity": "Common",
            "drop_requirements": null
        },
        {
            "id": null,
            "name": "Fire rune",
            "quantity": "37",
            "rarity": "Uncommon",
            "drop_requirements": null
        },
        {
            "id": null,
            "name": "Chaos rune",
            "quantity": "5,10,12",
            "rarity": "Uncommon",
            "drop_requirements": null
        },
        {
            "id": null,
            "name": "Blood rune",
            "quantity": "7",
            "rarity": "Uncommon",
            "drop_requirements": null
        },
        {
            "id": null,
            "name": "Law rune",
            "quantity": "3-4",
            "rarity": "Rare",
            "drop_requirements": null
        },
        {
            "id": null,
            "name": "Coins",
            "quantity": "30,44,132,200,220,460",
            "rarity": "Common",
            "drop_requirements": null
        },
        {
            "id": null,
            "name": "Adamantite bar",
            "quantity": "1",
            "rarity": "Uncommon",
            "drop_requirements": null
        },
        {
            "id": null,
            "name": "Lobster",
            "quantity": "1",
            "rarity": "Uncommon",
            "drop_requirements": null
        },
        {
            "id": null,
            "name": "Defence potion(3)",
            "quantity": "1",
            "rarity": "Rare",
            "drop_requirements": null
        },
        {
            "id": null,
            "name": "Ancient shard",
            "quantity": "1",
            "rarity": "Rare",
            "drop_requirements": "<ref  group=d name=\"catacomb\">Only dropped by those found within the [[Catacombs of Kourend]].</ref><br/><small>Lv 178: (1/226.66)<br/>Lv 184: (1/220)</small>"
        },
        {
            "id": null,
            "name": "Dark totem base",
            "quantity": "1",
            "rarity": "Rare",
            "drop_requirements": "<ref group=d name=\"catacomb\" /><br/><small>Lv 178: (1/340)<br/>Lv 184: (1/330)</small>"
        },
        {
            "id": null,
            "name": "Dark totem middle",
            "quantity": "1",
            "rarity": "Rare",
            "drop_requirements": "<ref group=d name=\"catacomb\" /><br/><small>Lv 178: (1/340)<br/>Lv 184: (1/330)</small>"
        },
        {
            "id": null,
            "name": "Dark totem top",
            "quantity": "1",
            "rarity": "Rare",
            "drop_requirements": "<ref group=d name=\"catacomb\" /><br/><small>Lv 178: (1/340)<br/>Lv 184: (1/330)</small>"
        },
        {
            "id": null,
            "name": "Adamant dagger",
            "quantity": "1",
            "rarity": "Uncommon",
            "drop_requirements": null
        },
        {
            "id": null,
            "name": "Adamant battleaxe",
            "quantity": "1",
            "rarity": "Uncommon",
            "drop_requirements": null
        },
        {
            "id": null,
            "name": "Adamant platebody",
            "quantity": "1",
            "rarity": "Uncommon",
            "drop_requirements": null
        },
        {
            "id": null,
            "name": "Rune full helm",
            "quantity": "1",
            "rarity": "Uncommon",
            "drop_requirements": null
        },
        {
            "id": null,
            "name": "Rune dagger",
            "quantity": "1",
            "rarity": "Rare",
            "drop_requirements": null
        },
        {
            "id": null,
            "name": "Rune sword",
            "quantity": "1",
            "rarity": "Rare",
            "drop_requirements": null
        },
        {
            "id": null,
            "name": "Chaos rune",
            "quantity": "25",
            "rarity": "Common",
            "drop_requirements": null
        },
        {
            "id": null,
            "name": "Death rune",
            "quantity": "5",
            "rarity": "Common",
            "drop_requirements": null
        },
        {
            "id": null,
            "name": "Blood rune",
            "quantity": "7",
            "rarity": "Uncommon",
            "drop_requirements": null
        },
        {
            "id": null,
            "name": "Law rune",
            "quantity": "15",
            "rarity": "Rare",
            "drop_requirements": null
        },
        {
            "id": null,
            "name": "Coins",
            "quantity": "250-899",
            "rarity": "Common",
            "drop_requirements": null
        },
        {
            "id": null,
            "name": "Shark",
            "quantity": "1",
            "rarity": "Uncommon",
            "drop_requirements": null
        },
        {
            "id": null,
            "name": "Adamantite ore",
            "quantity": "2 (noted)",
            "rarity": "Uncommon",
            "drop_requirements": null
        },
        {
            "id": null,
            "name": "Adamantite bar",
            "quantity": "2 (noted)",
            "rarity": "Uncommon",
            "drop_requirements": null
        }
    ],
    "rare_drop_table": null
}