{"url": "http://2007.runescape.wikia.com/wiki/Light_bow_tie", "id": 19985, "caption": "Light bow tie", "release_date": "06 July 2016", "members_only": 1, "quest_item": 0, "tradeable": 1, "equipable": 1, "stackable": 0, "high_alch": 3000, "low_alch": 2000, "destroy": "Drop", "store_price": 0, "weight": 0.0, "examine": "Bow ties are cool.", "edible": 0, "ge_price": 0, "buy_limit": 0, "attack_stab": "+0", "attack_slash": "+0", "attack_crush": "+0", "attack_magic": "+0", "attack_ranged": "+0", "defence_stab": "+0", "defence_slash": "+0", "defence_crush": "+0", "defence_magic": "+0", "defence_ranged": "+0", "melee_strength": "+0", "ranged_strength": "0", "magic_damage": "0%", "prayer": "+0"}