{
    "id": 10175,
    "name": "Golden feather",
    "members": true,
    "tradeable": false,
    "tradeable_on_ge": false,
    "stackable": false,
    "noted": false,
    "noteable": false,
    "linked_id": null,
    "placeholder": false,
    "equipable": false,
    "equipable_by_player": false,
    "cost": 1,
    "lowalch": 0,
    "highalch": 0,
    "weight": 0.001,
    "buy_limit": null,
    "quest_item": true,
    "release_date": "28 November 2006",
    "examine": "An intricate feather crafted from a gold-coloured metal of some sort.",
    "url": "https://oldschool.runescape.wiki/w/Golden_feather_(Eagles%27_Peak)",
    "equipment": null
}