{
    "id": 10952,
    "name": "Slayer bell",
    "incomplete": false,
    "members": true,
    "tradeable": true,
    "tradeable_on_ge": true,
    "stackable": false,
    "noted": false,
    "noteable": true,
    "linked_id_item": null,
    "linked_id_noted": 10953,
    "linked_id_placeholder": 14020,
    "placeholder": false,
    "equipable": false,
    "equipable_by_player": false,
    "equipable_weapon": false,
    "cost": 150,
    "lowalch": 60,
    "highalch": 90,
    "weight": 0.028,
    "buy_limit": 40,
    "quest_item": false,
    "release_date": "2007-03-20",
    "duplicate": false,
    "examine": "Don't make anyone jump when you ring this!",
    "wiki_name": "Slayer bell",
    "wiki_url": "https://oldschool.runescape.wiki/w/Slayer_bell",
    "equipment": null,
    "weapon": null
}