{
    "id": 115,
    "name": "Strength potion(3)",
    "members": false,
    "tradeable": true,
    "tradeable_on_ge": true,
    "stackable": false,
    "noted": false,
    "noteable": true,
    "linked_id": 116,
    "equipable": false,
    "equipable_by_player": false,
    "cost": 13,
    "lowalch": 5,
    "highalch": 7,
    "weight": 0.03,
    "buy_limit": 2000,
    "quest_item": false,
    "release_date": "05 February 2001",
    "examine": "3 doses of Strength potion.",
    "url": "https://oldschool.runescape.wiki/w/Strength_potion"
}