{
    "id": 13117,
    "name": "Falador shield 1",
    "members": true,
    "tradeable": false,
    "stackable": false,
    "noted": false,
    "noteable": false,
    "equipable": true,
    "cost": 0,
    "lowalch": 0,
    "highalch": 0,
    "weight": 5.0,
    "buy_limit": null,
    "quest_item": null,
    "release_date": "05 March 2015",
    "examine": [
        "A shield from Falador."
    ],
    "url": "http://oldschoolrunescape.wikia.com/wiki/Falador_shield_1",
    "bonuses": {
        "attack_stab": 0,
        "attack_slash": 0,
        "attack_crush": 0,
        "attack_magic": -8,
        "attack_ranged": -2,
        "defence_stab": 8,
        "defence_slash": 10,
        "defence_crush": 9,
        "defence_magic": -1,
        "defence_ranged": 9,
        "melee_strength": 0,
        "ranged_strength": 0,
        "magic_damage": 0,
        "prayer": 1,
        "slot": "shield",
        "attack_speed": 0
    }
}