{
    "id": 18553,
    "name": "Treachery of royalty",
    "members": false,
    "tradeable": false,
    "tradeable_on_ge": false,
    "stackable": false,
    "noted": false,
    "noteable": false,
    "linked_id": null,
    "equipable": false,
    "cost": 0,
    "lowalch": 0,
    "highalch": 0,
    "weight": 0.0,
    "buy_limit": null,
    "quest_item": false,
    "release_date": "07 January 2016",
    "examine": "The Treachery of Royalty, by Professor Answith.",
    "url": "https://oldschool.runescape.wiki/w/Treachery_of_royalty"
}