{
    "id": 2,
    "name": "Cannonball",
    "members": true,
    "tradeable": true,
    "tradeable_on_ge": true,
    "stackable": true,
    "noted": false,
    "noteable": false,
    "linked_id": null,
    "placeholder": false,
    "equipable": false,
    "equipable_by_player": false,
    "cost": 5,
    "lowalch": 2,
    "highalch": 3,
    "weight": 0.0,
    "buy_limit": 7000,
    "quest_item": false,
    "release_date": "27 May 2003",
    "examine": "Ammo for the Dwarf Cannon.",
    "url": "https://oldschool.runescape.wiki/w/Cannonball"
}