{
    "id": 20272,
    "name": "Cabbage round shield",
    "members": true,
    "tradeable": true,
    "stackable": false,
    "noted": false,
    "noteable": true,
    "equipable": true,
    "cost": 3000,
    "lowalch": 1200,
    "highalch": 1800,
    "weight": 4.0,
    "buy_limit": 125,
    "quest_item": null,
    "release_date": "06 July 2016",
    "examine": "An adamant shield shaped like a cabbage.",
    "url": "https://oldschool.runescape.wiki/w/Cabbage_round_shield",
    "bonuses": {
        "attack_stab": 0,
        "attack_slash": 0,
        "attack_crush": 0,
        "attack_magic": -6,
        "attack_ranged": -2,
        "defence_stab": 24,
        "defence_slash": 26,
        "defence_crush": 22,
        "defence_magic": 0,
        "defence_ranged": 24,
        "melee_strength": 0,
        "ranged_strength": 0,
        "magic_damage": 0,
        "prayer": 0
    },
    "equipment": {
        "slot": "shield",
        "attack_speed": null,
        "skill_reqs": null
    }
}