{
    "id": 21712,
    "name": "Spectral potion",
    "members": false,
    "tradeable": false,
    "tradeable_on_ge": false,
    "stackable": false,
    "noted": false,
    "noteable": false,
    "linked_id": null,
    "placeholder": false,
    "equipable": false,
    "equipable_by_player": false,
    "cost": 0,
    "lowalch": 0,
    "highalch": 0,
    "weight": 0.0,
    "buy_limit": null,
    "quest_item": false,
    "release_date": "19 October 2017",
    "examine": "A potion that emanates with dark, ghostly power.",
    "url": "https://oldschool.runescape.wiki/w/Spectral_potion"
}