{
    "id": 21801,
    "name": "Enchanted symbol",
    "members": false,
    "tradeable": false,
    "stackable": false,
    "noted": false,
    "noteable": false,
    "equipable": false,
    "cost": 0,
    "lowalch": 0,
    "highalch": 0,
    "weight": 0.0,
    "buy_limit": null,
    "quest_item": [
        "The Mage Arena II"
    ],
    "release_date": "23 November 2017",
    "examine": "A magical symbol used to locate demons in the Wilderness.",
    "url": "https://oldschool.runescape.wiki/w/Enchanted_symbol"
}