{
    "id": 2313,
    "name": "Pie dish",
    "members": false,
    "tradeable": true,
    "tradeable_on_ge": true,
    "stackable": false,
    "noted": false,
    "noteable": true,
    "linked_id": 2314,
    "placeholder": false,
    "equipable": false,
    "equipable_by_player": false,
    "cost": 3,
    "lowalch": 1,
    "highalch": 1,
    "weight": 0.1,
    "buy_limit": 500,
    "quest_item": false,
    "release_date": "17 March 2001",
    "examine": "Deceptively pie shaped.",
    "url": "https://oldschool.runescape.wiki/w/Pie_dish",
    "equipment": null
}