{
    "id": 4031,
    "name": "Karamjan monkey greegree",
    "members": true,
    "tradeable": false,
    "stackable": false,
    "noted": false,
    "noteable": false,
    "equipable": false,
    "cost": 500,
    "lowalch": 200,
    "highalch": 300,
    "weight": 0.0,
    "buy_limit": null,
    "quest_item": [
        "Monkey Madness I"
    ],
    "release_date": "06 December 2004",
    "examine": [
        "A magical talisman in the shape of a Karamjan monkey head."
    ],
    "url": "http://oldschoolrunescape.wikia.com/wiki/Karamjan_monkey_greegree"
}