{
    "id": 5483,
    "name": "Curry seedling",
    "members": true,
    "tradeable": false,
    "tradeable_on_ge": false,
    "stackable": false,
    "noted": false,
    "noteable": false,
    "linked_id_item": null,
    "linked_id_noted": null,
    "linked_id_placeholder": 13829,
    "placeholder": false,
    "equipable": false,
    "equipable_by_player": false,
    "equipable_weapon": false,
    "cost": 1,
    "lowalch": 0,
    "highalch": 0,
    "weight": 0.907,
    "buy_limit": null,
    "quest_item": false,
    "release_date": "2005-07-11",
    "duplicate": false,
    "examine": "A curry tree seed has been sown in this plant pot.",
    "wiki_name": "Curry seedling (Unwatered)",
    "wiki_url": "https://oldschool.runescape.wiki/w/Curry_seedling#Unwatered",
    "equipment": null,
    "weapon": null
}