{
    "id": 7801,
    "name": "Snake hide",
    "members": true,
    "tradeable": true,
    "stackable": false,
    "noted": false,
    "noteable": true,
    "equipable": false,
    "cost": 35,
    "lowalch": 14,
    "highalch": 21,
    "weight": 0.5,
    "buy_limit": null,
    "quest_item": null,
    "release_date": "09 August 2005",
    "examine": [
        "Scaly but not slimy! It could be a useful material if it were tanned."
    ],
    "url": "http://oldschoolrunescape.wikia.com/wiki/Snake_hide"
}