{
  "id": 9925,
  "name": "Skeleton mask",
  "tradeable": false,
  "stackable": false,
  "noteable": false,
  "equipable": true,
  "members": false,
  "weight": 2.0,
  "buy_limit": -1,
  "quest_item": true,
  "release_date": "30 October 2006",
  "cost": 1,
  "lowalch": 0,
  "highalch": 0,
  "examine": "A scary skeleton mask.",
  "url": "http://2007.runescape.wikia.com/wiki/Skeleton_mask",
  "bonuses": {
    "attack_slash": 0,
    "defence_crush": 0,
    "prayer": 0,
    "attack_stab": 0,
    "ranged_strength": 0,
    "attack_ranged": 0,
    "defence_magic": 0,
    "melee_strength": 0,
    "defence_ranged": 0,
    "defence_stab": 0,
    "defence_slash": 0,
    "attack_magic": 0,
    "attack_crush": 0,
    "magic_damage": 0
  },
  "item_slot": "head"
}